grahamstools/__init__.py
grahamstools/module1.py
grahamstools/move_mouse.py
grahamstools-0.1.4.dist-info/METADATA
grahamstools-0.1.4.dist-info/WHEEL
grahamstools-0.1.4.dist-info/top_level.txt
grahamstools-0.1.4.dist-info/RECORD
