Metadata-Version: 2.1
Name: grahamstools
Version: 0.1.4
Summary: Tools and resources for Python developers
Home-page: https://github.com/GrahamboJangles/GrahamsTools
Download-URL: https://github.com/GrahamboJangles/GrahamsTools/archive/refs/tags/0.1.0.tar.gz
Author: GrahamboJangles
Author-email: lafebregraham@gmail.com
Classifier: Programming Language :: Python :: 3
Classifier: License :: OSI Approved :: MIT License
Classifier: Operating System :: OS Independent
Classifier: Development Status :: 1 - Planning
Classifier: Intended Audience :: Developers
Classifier: Topic :: Software Development :: Build Tools
Requires-Python: >=3.6
